bravo_python_sdk/__init__.py
bravo_python_sdk/factor.py
bravo_python_sdk/factor_modules/FaceModule.py
bravo_python_sdk/factor_modules/__init__.py
bravo_python_sdk/handler/__init__.py
bravo_python_sdk/handler/nativeMethods.py
bravo_python_sdk/handler/lib/__init__.py
bravo_python_sdk/helper/__init__.py
bravo_python_sdk/helper/decorators.py
bravo_python_sdk/helper/messages.py
bravo_python_sdk/helper/utils.py
bravo_python_sdk/helper/result_objects/__init__.py
bravo_python_sdk/helper/result_objects/compareResult.py
bravo_python_sdk/helper/result_objects/deleteResult.py
bravo_python_sdk/helper/result_objects/enrollPredictResult.py
bravo_python_sdk/helper/result_objects/faceObjectResult.py
bravo_python_sdk/helper/result_objects/faceValidationResult.py
bravo_python_sdk/helper/result_objects/isoFaceResult.py
bravo_python_sdk/settings/__init__.py
bravo_python_sdk/settings/cacheType.py
bravo_python_sdk/settings/configuration.py
bravo_python_sdk/settings/loggingLevel.py
bravo_python_sdk/settings/supportedPlatforms.py
bravo_python_sdk-1.1.0.dist-info/LICENSE
bravo_python_sdk-1.1.0.dist-info/METADATA
bravo_python_sdk-1.1.0.dist-info/WHEEL
bravo_python_sdk-1.1.0.dist-info/top_level.txt
bravo_python_sdk-1.1.0.dist-info/RECORD
