Metadata-Version: 2.1
Name: bravo-python-sdk
Version: 1.1.0
Summary: Bravo SDK Library for Python
Home-page: https://privateid.com/
Author: Private Identity
Author-email: support@private.id
Project-URL: Bug Reports, https://github.com/prividentity/cryptonets-python-sdk/issues
Project-URL: Source, https://github.com/prividentity/cryptonets-python-sdk
Project-URL: Documentation, https://docs.private.id/cryptonets-python-sdk/index.html
Project-URL: Release Notes, https://docs.private.id/cryptonets-python-sdk/changelog.html
Keywords: privateid,cryptonets,face identification
Platform: any
Classifier: Intended Audience :: Developers
Classifier: License :: Other/Proprietary License
Classifier: Programming Language :: Python
Classifier: Programming Language :: Python :: 3
Classifier: Programming Language :: Python :: 3.6
Classifier: Programming Language :: Python :: 3.7
Classifier: Programming Language :: Python :: 3.8
Classifier: Programming Language :: Python :: 3.9
Classifier: Topic :: Software Development
Requires-Python: >=3.6
License-File: LICENSE
Requires-Dist: numpy (>=1.21.0)
Requires-Dist: pillow (>=9.1.0)
Requires-Dist: boto3
Requires-Dist: tqdm
